.DS_Store
investpy/.DS_Store
investpy/__init__.py
investpy/bonds.py
investpy/certificates.py
investpy/commodities.py
investpy/crypto.py
investpy/currency_crosses.py
investpy/etfs.py
investpy/funds.py
investpy/indices.py
investpy/news.py
investpy/search.py
investpy/stocks.py
investpy/technical.py
investpy/zyte.pem
investpy/data/__init__.py
investpy/data/bonds_data.py
investpy/data/certificates_data.py
investpy/data/commodities_data.py
investpy/data/crypto_data.py
investpy/data/currency_crosses_data.py
investpy/data/etfs_data.py
investpy/data/funds_data.py
investpy/data/indices_data.py
investpy/data/stocks_data.py
investpy/resources/.DS_Store
investpy/resources/bonds.csv
investpy/resources/certificates.csv
investpy/resources/commodities.csv
investpy/resources/cryptos.csv
investpy/resources/currency_crosses.csv
investpy/resources/etfs.csv
investpy/resources/funds.csv
investpy/resources/indices.csv
investpy/resources/stocks.csv
investpy/resources/zyte-proxy-ca.crt
investpy/resources/zyte.pem
investpy/utils/__init__.py
investpy/utils/constant.py
investpy/utils/data.py
investpy/utils/extra.py
investpy/utils/search_obj.py
tests/__init__.py
tests/requirements.txt
tests/test_investpy.py
tests/test_investpy_errors.py
investpyx-0.1.5.dist-info/LICENSE
investpyx-0.1.5.dist-info/METADATA
investpyx-0.1.5.dist-info/WHEEL
investpyx-0.1.5.dist-info/top_level.txt
investpyx-0.1.5.dist-info/RECORD
