Metadata-Version: 2.1
Name: investpyx
Version: 0.1.5
Summary: This is a fork of investpy library, and is intended for testing purpose only. All descriptions are hence of original investpy library. Please support the original Author for the contribution he made by developing the investpy library.
Home-page: https://investpy.readthedocs.io/
Author: Original Author: Alvaro Bartolome, Author of Extended Feature: Komal Paudyal
Author-email: alvarobdc@yahoo.com, komal.paudyal@icloud.com
License: MIT License
Download-URL: https://github.com/alvarobartt/investpy/archive/1.0.3.tar.gz
Project-URL: Source, https://github.com/alvarobartt/investpy
Project-URL: Documentation, https://investpy.readthedocs.io/
Project-URL: Bug Reports, https://github.com/alvarobartt/investpy/issues
Project-URL: Forked (Extended Feature), https://github.com/lively-ops/investpy
Keywords: investing,investing-api,historical-data,financial-data,stocks,funds,etfs,indices,currency crosses,bonds,commodities,crypto currencies
Platform: UNKNOWN
Classifier: Development Status :: 4 - Beta
Classifier: Programming Language :: Python :: 3 :: Only
Classifier: Programming Language :: Python :: 3.6
Classifier: Programming Language :: Python :: 3.7
Classifier: Programming Language :: Python :: 3.8
Classifier: Programming Language :: Python :: 3.9
Classifier: License :: OSI Approved :: MIT License
Classifier: Intended Audience :: Developers
Classifier: Topic :: Office/Business :: Financial
Classifier: Topic :: Office/Business :: Financial :: Investment
Classifier: Topic :: Scientific/Engineering :: Information Analysis
Classifier: Topic :: Software Development :: Libraries
Requires-Python: >=3
Requires-Dist: Unidecode (>=1.1.1)
Requires-Dist: setuptools (>=41.2.0)
Requires-Dist: numpy (>=1.17.2)
Requires-Dist: pandas (>=0.25.1)
Requires-Dist: lxml (>=4.4.1)
Requires-Dist: requests (>=2.22.0)
Requires-Dist: pytz (>=2019.3)
Provides-Extra: docs
Requires-Dist: sphinx (==2.4.4) ; extra == 'docs'
Requires-Dist: sphinx-rtd-theme (==0.4.3) ; extra == 'docs'
Requires-Dist: recommonmark (==0.6.0) ; extra == 'docs'
Provides-Extra: tests
Requires-Dist: pytest (==6.1.1) ; extra == 'tests'
Requires-Dist: codecov (==2.1.10) ; extra == 'tests'
Requires-Dist: pytest-cov (==2.10.1) ; extra == 'tests'
